MANIFEST.in
README.txt
setup.py
Products/.DS_Store
Products/__init__.py
Products/interfaces.py
Products.Vees.egg-info/PKG-INFO
Products.Vees.egg-info/SOURCES.txt
Products.Vees.egg-info/dependency_links.txt
Products.Vees.egg-info/entry_points.txt
Products.Vees.egg-info/namespace_packages.txt
Products.Vees.egg-info/not-zip-safe
Products.Vees.egg-info/requires.txt
Products.Vees.egg-info/top_level.txt
Products/Vees/Vee.py
Products/Vees/__init__.py
Products/Vees/config.py
Products/Vees/configure.zcml
Products/Vees/interfaces.py
Products/Vees/tests.py
Products/Vees/vee-view.pt
Products/Vees/version.txt
Products/Vees/views.py
Products/Vees/profiles/default/factorytool.xml
Products/Vees/profiles/default/metadata.xml
Products/Vees/profiles/default/skins.xml
Products/Vees/profiles/default/types.xml
Products/Vees/profiles/default/types/Vee.xml
Products/Vees/skins/.DS_Store
Products/Vees/skins/Vees/.DS_Store
Products/Vees/skins/Vees/vee.png
docs/HISTORY.txt
docs/INSTALL.txt
docs/LICENSE.GPL
docs/LICENSE.txt