Metadata-Version: 1.0
Name: Products.Vees
Version: 1.1
Summary: Vee Map products
Home-page: http://svn.plone.org/svn/collective/
Author: Nathan Van Gheem
Author-email: vangheem@gmail.com
License: GPL
Platform: UNKNOWN
Classifier: Framework :: Plone
Classifier: Programming Language :: Python
